allcopol/__init__.py
allcopol/align_clusters.py
allcopol/allcopol.py
allcopol/create_indfile.py
allcopol/relabel_trees.py
allcopol/utils/__init__.py
allcopol/utils/optimization.py
allcopol/utils/phylonet.py
allcopol/utils/utils.py
allcopol-0.1.2.dist-info/LICENSE
allcopol-0.1.2.dist-info/METADATA
allcopol-0.1.2.dist-info/WHEEL
allcopol-0.1.2.dist-info/entry_points.txt
allcopol-0.1.2.dist-info/top_level.txt
allcopol-0.1.2.dist-info/RECORD
