Metadata-Version: 2.1
Name: allcopol
Version: 0.1.2
Summary: AllCoPol: Inferring allele co-ancestry in polyploids
Home-page: https://github.com/AGOberprieler/allcopol
Author: Ulrich Lautenschlager
Author-email: ulrich.lautenschlager@ur.de
License: MIT
Platform: UNKNOWN
Requires-Python: >=3.5
Requires-Dist: argparse
Requires-Dist: biopython
Requires-Dist: configargparse
Requires-Dist: numpy
Requires-Dist: scipy
